twembeddings/__init__.py
twembeddings/build_features_matrix.py
twembeddings/clustering_algo.py
twembeddings/embeddings.py
twembeddings/eval.py
twembeddings/stop_words.py
twembeddings-0.4.0.dist-info/LICENSE
twembeddings-0.4.0.dist-info/METADATA
twembeddings-0.4.0.dist-info/WHEEL
twembeddings-0.4.0.dist-info/top_level.txt
twembeddings-0.4.0.dist-info/RECORD
