Metadata-Version: 2.1
Name: twembeddings
Version: 0.4.0
Summary: event detection in tweets
Home-page: https://github.com/ina-foss/twembeddings
Author: Béatrice Mazoyer
Author-email: beatrice.mazoyer@sciencespo.fr
License: MIT
License-File: LICENSE
Requires-Dist: gensim
Requires-Dist: numpy
Requires-Dist: pandas
Requires-Dist: protobuf ==3.20.3
Requires-Dist: pytorch-transformers
Requires-Dist: scikit-learn >=1.3
Requires-Dist: scipy
Requires-Dist: sentence-transformers
Requires-Dist: tensorflow >=2.13.0
Requires-Dist: tensorflow-text >=2.13.0
Requires-Dist: tqdm
Requires-Dist: unidecode
Requires-Dist: twython
Requires-Dist: pyyaml
Requires-Dist: sparse-dot-mkl
